[
    {
        "product_id": 1,
        "product_title": "Dell XPS 13",
        "product_image": "https://i.postimg.cc/7hY5qsHv/Dell-XPS-13.jpg",
        "category": "Laptops",
        "price": 999.99,
        "description": "A powerful laptop with a sleek design.",
        "Specification": [
            "Intel Core i7",
            "16GB RAM",
            "512GB SSD"
        ],
        "availability": true,
        "rating": 4.7
    },
    {
        "product_id": 2,
        "product_title": "Lenovo Gaming",
        "product_image": "https://i.postimg.cc/SQzKRND1/Lenovo-Idea-Pad-Gaming.jpg",
        "category": "Laptops",
        "price": 1500.99,
        "description": "Professional laptop with exceptional performance.",
        "Specification": [
            "Apple M1 Pro",
            "32GB RAM",
            "1TB SSD"
        ],
        "availability": true,
        "rating": 4.9
    },
    {
        "product_id": 3,
        "product_title": "HP Spectre x360",
        "product_image": "https://i.postimg.cc/0jWbjYjz/HP-Spectre-x360.jpg",
        "category": "Laptops",
        "price": 1349.99,
        "description": "A convertible laptop with stunning design.",
        "Specification": [
            "Intel Core i7",
            "16GB RAM",
            "512GB SSD"
        ],
        "availability": true,
        "rating": 4.6
    },
    {
        "product_id": 4,
        "product_title": "Asus ZenBook 14",
        "product_image": "https://i.postimg.cc/bJRGccjH/Asus-Zen-Book-14.jpg",
        "category": "Laptops",
        "price": 849.99,
        "description": "Thin and lightweight laptop for on-the-go users.",
        "Specification": [
            "Intel Core i5",
            "8GB RAM",
            "256GB SSD"
        ],
        "availability": true,
        "rating": 4.5
    },
    {
        "product_id": 5,
        "product_title": "Lenovo ThinkPad",
        "product_image": "https://i.postimg.cc/kXH2dvLZ/Lenovo-Think-Pad-X1-Carbon.jpg",
        "category": "Laptops",
        "price": 1499.99,
        "description": "Business laptop with durability and performance.",
        "Specification": [
            "Intel Core i7",
            "16GB RAM",
            "1TB SSD"
        ],
        "availability": true,
        "rating": 4.8
    },
    {
        "product_id": 6,
        "product_title": "Acer Aspire 5",
        "product_image": "https://i.postimg.cc/SNx94sRX/Acer-Aspire-5.jpg",
        "category": "Laptops",
        "price": 599.99,
        "description": "Budget-friendly laptop for everyday use.",
        "Specification": [
            "AMD Ryzen 5",
            "8GB RAM",
            "512GB SSD"
        ],
        "availability": true,
        "rating": 4.4
    },
    {
        "product_id": 7,
        "product_title": "Apple MacBook Air",
        "product_image": "https://i.postimg.cc/TYND365t/Apple-Mac-Book-Air.jpg",
        "category": "MacBook",
        "price": 999.99,
        "description": "Lightweight and powerful laptop for students.",
        "Specification": [
            "Apple M1 Chip",
            "8GB RAM",
            "256GB SSD"
        ],
        "availability": true,
        "rating": 4.8
    },
    {
        "product_id": 8,
        "product_title": "Apple MacBook 14",
        "product_image": "https://i.postimg.cc/4xKhKSzs/Apple-Mac-Book-Pro-14.jpg",
        "category": "MacBook",
        "price": 1999.99,
        "description": "Compact laptop with high-end specifications.",
        "Specification": [
            "Apple M1 Pro",
            "16GB RAM",
            "512GB SSD"
        ],
        "availability": true,
        "rating": 4.9
    },
    {
        "product_id": 9,
        "product_title": "Samsung Galaxy S21",
        "product_image": "https://i.postimg.cc/8Pc730XM/Samsung-Galaxy-S21.jpg",
        "category": "Phones",
        "price": 799.99,
        "description": "Flagship smartphone with exceptional camera.",
        "Specification": [
            "8GB RAM",
            "128GB Storage",
            "4000mAh Battery"
        ],
        "availability": true,
        "rating": 4.7
    },
    {
        "product_id": 10,
        "product_title": "iPhone 13",
        "product_image": "https://i.postimg.cc/WpXD5v8s/i-Phone-13.jpg",
        "category": "Phones",
        "price": 899.99,
        "description": "The latest iPhone with advanced features.",
        "Specification": [
            "A15 Bionic chip",
            "128GB Storage",
            "3095mAh Battery"
        ],
        "availability": true,
        "rating": 4.8
    },
    {
        "product_id": 11,
        "product_title": "Apple Watch Series 7",
        "product_image": "https://i.postimg.cc/ydKJb628/Apple-Watch-Series-7.jpg",
        "category": "Smart Watches",
        "price": 399.99,
        "description": "Smartwatch with fitness tracking features.",
        "Specification": [
            "Fitness Tracking",
            "Blood Oxygen Monitoring",
            "Always-On Display"
        ],
        "availability": true,
        "rating": 4.6
    },
    {
        "product_id": 12,
        "product_title": "Samsung Watch",
        "product_image": "https://i.postimg.cc/XYTB9k8F/Samsung-Galaxy-Watch-4.jpg",
        "category": "Smart Watches",
        "price": 249.99,
        "description": "Smartwatch with health monitoring features.",
        "Specification": [
            "Body Composition Measurement",
            "Fitness Tracking",
            "GPS"
        ],
        "availability": true,
        "rating": 4.5
    }
]